{
    "narrations": [
        {
            "timestamp_sec": 600.7712009546634,
            "timestamp_frame": 18023,
            "_unmapped_timestamp_sec": 600.79223,
            "narration_text": "#C C drives the hammer in his right hand on the nut in the gear axle. #unsure",
            "annotation_uid": "ac221de3-5efa-4e93-a2fe-0a6c8dcd6714"
        },
        {
            "timestamp_sec": 603.2403809546634,
            "timestamp_frame": 18097,
            "_unmapped_timestamp_sec": 603.26141,
            "narration_text": "#C C swipes the shaft of the gear axle with his left hand. #unsure",
            "annotation_uid": "ac221de3-5efa-4e93-a2fe-0a6c8dcd6714"
        },
        {
            "timestamp_sec": 605.6078109546634,
            "timestamp_frame": 18168,
            "_unmapped_timestamp_sec": 605.62884,
            "narration_text": "#C C loosens a crankshaft in the gear axle with his left hand. #unsure",
            "annotation_uid": "ac221de3-5efa-4e93-a2fe-0a6c8dcd6714"
        },
        {
            "timestamp_sec": 607.6031409546634,
            "timestamp_frame": 18227,
            "_unmapped_timestamp_sec": 607.62417,
            "narration_text": "#C C drops a hammer on the table with his right hand.",
            "annotation_uid": "ac221de3-5efa-4e93-a2fe-0a6c8dcd6714"
        },
        {
            "timestamp_sec": 607.3520709546634,
            "timestamp_frame": 18220,
            "_unmapped_timestamp_sec": 607.3731,
            "narration_text": "#C C holds the crankshaft with his left hand. #unsure",
            "annotation_uid": "ac221de3-5efa-4e93-a2fe-0a6c8dcd6714"
        },
        {
            "timestamp_sec": 609.5906009546634,
            "timestamp_frame": 18287,
            "_unmapped_timestamp_sec": 609.61163,
            "narration_text": "#C C turns the shaft of the gear axle with his right hand. #unsure",
            "annotation_uid": "ac221de3-5efa-4e93-a2fe-0a6c8dcd6714"
        },
        {
            "timestamp_sec": 614.4579109546634,
            "timestamp_frame": 18433,
            "_unmapped_timestamp_sec": 614.47894,
            "narration_text": "#C C cleans his right hand on the issue in his left hand.",
            "annotation_uid": "ac221de3-5efa-4e93-a2fe-0a6c8dcd6714"
        },
        {
            "timestamp_sec": 615.5865809546634,
            "timestamp_frame": 18467,
            "_unmapped_timestamp_sec": 615.60761,
            "narration_text": "#C C holds the shaft of the gear axle with his right hand. #unsure",
            "annotation_uid": "ac221de3-5efa-4e93-a2fe-0a6c8dcd6714"
        },
        {
            "timestamp_sec": 615.5865809546634,
            "timestamp_frame": 18467,
            "_unmapped_timestamp_sec": 615.60761,
            "narration_text": "#C C holds the crankshaft with his left hand. #unsure",
            "annotation_uid": "ac221de3-5efa-4e93-a2fe-0a6c8dcd6714"
        },
        {
            "timestamp_sec": 616.9906909546634,
            "timestamp_frame": 18509,
            "_unmapped_timestamp_sec": 617.01172,
            "narration_text": "#C C picks a on the clutch on the table with his right hand. #unsure",
            "annotation_uid": "ac221de3-5efa-4e93-a2fe-0a6c8dcd6714"
        },
        {
            "timestamp_sec": 618.4263009546634,
            "timestamp_frame": 18552,
            "_unmapped_timestamp_sec": 618.44733,
            "narration_text": "#C holds the clutch with both hands. #unsure",
            "annotation_uid": "ac221de3-5efa-4e93-a2fe-0a6c8dcd6714"
        },
        {
            "timestamp_sec": 624.3472609546634,
            "timestamp_frame": 18730,
            "_unmapped_timestamp_sec": 624.36829,
            "narration_text": "#C C moves the hammer on the table with his right hand.",
            "annotation_uid": "ac221de3-5efa-4e93-a2fe-0a6c8dcd6714"
        },
        {
            "timestamp_sec": 625.9876209546634,
            "timestamp_frame": 18779,
            "_unmapped_timestamp_sec": 626.00865,
            "narration_text": "#C C picks a bolt from a tool shelf with his right hand. ",
            "annotation_uid": "ac221de3-5efa-4e93-a2fe-0a6c8dcd6714"
        },
        {
            "timestamp_sec": 630.5610009546634,
            "timestamp_frame": 18916,
            "_unmapped_timestamp_sec": 630.58203,
            "narration_text": "#C C screws the bolt into the clutch with his right hand. #unsure",
            "annotation_uid": "ac221de3-5efa-4e93-a2fe-0a6c8dcd6714"
        },
        {
            "timestamp_sec": 627.8218009546634,
            "timestamp_frame": 18834,
            "_unmapped_timestamp_sec": 627.84283,
            "narration_text": "#C C places the clutch on the table with his left hand. #unsure",
            "annotation_uid": "ac221de3-5efa-4e93-a2fe-0a6c8dcd6714"
        },
        {
            "timestamp_sec": 628.8143609546634,
            "timestamp_frame": 18864,
            "_unmapped_timestamp_sec": 628.83539,
            "narration_text": "#C C screws the bolt with both hands.",
            "annotation_uid": "ac221de3-5efa-4e93-a2fe-0a6c8dcd6714"
        },
        {
            "timestamp_sec": 630.9774309546634,
            "timestamp_frame": 18929,
            "_unmapped_timestamp_sec": 630.99846,
            "narration_text": "#C C turns the gear cover upright with his right hand. #unsure",
            "annotation_uid": "ac221de3-5efa-4e93-a2fe-0a6c8dcd6714"
        },
        {
            "timestamp_sec": 632.0960109546634,
            "timestamp_frame": 18962,
            "_unmapped_timestamp_sec": 632.11704,
            "narration_text": "#C C screws the nut into the clutch with his right hand. #unsure",
            "annotation_uid": "ac221de3-5efa-4e93-a2fe-0a6c8dcd6714"
        },
        {
            "timestamp_sec": 634.4441609546634,
            "timestamp_frame": 19033,
            "_unmapped_timestamp_sec": 634.46519,
            "narration_text": "#C C drops the tissue on the table with his right hand.",
            "annotation_uid": "ac221de3-5efa-4e93-a2fe-0a6c8dcd6714"
        },
        {
            "timestamp_sec": 639.6331209546634,
            "timestamp_frame": 19188,
            "_unmapped_timestamp_sec": 639.65415,
            "narration_text": "#C C picks a spanner from a tool shelf with his right hand. ",
            "annotation_uid": "ac221de3-5efa-4e93-a2fe-0a6c8dcd6714"
        },
        {
            "timestamp_sec": 640.6405009546634,
            "timestamp_frame": 19219,
            "_unmapped_timestamp_sec": 640.66153,
            "narration_text": "#C C screws the bolt on the clutch with the spanner in his right hand.",
            "annotation_uid": "ac221de3-5efa-4e93-a2fe-0a6c8dcd6714"
        },
        {
            "timestamp_sec": 638.6891409546635,
            "timestamp_frame": 19160,
            "_unmapped_timestamp_sec": 638.7101700000001,
            "narration_text": "#C C moves the clutch from his right hand to his left hand. #unsure",
            "annotation_uid": "ac221de3-5efa-4e93-a2fe-0a6c8dcd6714"
        },
        {
            "timestamp_sec": 644.7700809546634,
            "timestamp_frame": 19342,
            "_unmapped_timestamp_sec": 644.79111,
            "narration_text": "#C C drops the spanner on the table with his right hand.",
            "annotation_uid": "ac221de3-5efa-4e93-a2fe-0a6c8dcd6714"
        },
        {
            "timestamp_sec": 645.5941009546634,
            "timestamp_frame": 19367,
            "_unmapped_timestamp_sec": 645.61513,
            "narration_text": "#C C moves a wire of a grader with his right hand. #unsure",
            "annotation_uid": "ac221de3-5efa-4e93-a2fe-0a6c8dcd6714"
        },
        {
            "timestamp_sec": 647.0072809546634,
            "timestamp_frame": 19410,
            "_unmapped_timestamp_sec": 647.02831,
            "narration_text": "#C C moves the grader with his right hand. #unsure",
            "annotation_uid": "ac221de3-5efa-4e93-a2fe-0a6c8dcd6714"
        },
        {
            "timestamp_sec": 648.5010109546635,
            "timestamp_frame": 19454,
            "_unmapped_timestamp_sec": 648.5220400000001,
            "narration_text": "#C C screws the bolt of the clutch using the grader with his right hand ",
            "annotation_uid": "ac221de3-5efa-4e93-a2fe-0a6c8dcd6714"
        },
        {
            "timestamp_sec": 648.3006809546633,
            "timestamp_frame": 19448,
            "_unmapped_timestamp_sec": 648.3217099999999,
            "narration_text": "#C C places the clutch on the bottom of the grader. #unsure",
            "annotation_uid": "ac221de3-5efa-4e93-a2fe-0a6c8dcd6714"
        },
        {
            "timestamp_sec": 653.9653709546634,
            "timestamp_frame": 19618,
            "_unmapped_timestamp_sec": 653.9864,
            "narration_text": "#C C picks a screwdriver from the table with his left hand.",
            "annotation_uid": "ac221de3-5efa-4e93-a2fe-0a6c8dcd6714"
        },
        {
            "timestamp_sec": 655.9773709546633,
            "timestamp_frame": 19679,
            "_unmapped_timestamp_sec": 655.9984,
            "narration_text": "#C C cleans the screwdriver with the tissue in his left hand.",
            "annotation_uid": "ac221de3-5efa-4e93-a2fe-0a6c8dcd6714"
        },
        {
            "timestamp_sec": 657.5753609546634,
            "timestamp_frame": 19727,
            "_unmapped_timestamp_sec": 657.59639,
            "narration_text": "#C C drops the tissue from the table with his left hand.",
            "annotation_uid": "ac221de3-5efa-4e93-a2fe-0a6c8dcd6714"
        },
        {
            "timestamp_sec": 658.6356609546634,
            "timestamp_frame": 19758,
            "_unmapped_timestamp_sec": 658.65669,
            "narration_text": "#C C removes a ring from the clutch using both hands. #unsure",
            "annotation_uid": "ac221de3-5efa-4e93-a2fe-0a6c8dcd6714"
        },
        {
            "timestamp_sec": 661.5876409546634,
            "timestamp_frame": 19847,
            "_unmapped_timestamp_sec": 661.60867,
            "narration_text": "#C C holds the ring with both hands.",
            "annotation_uid": "ac221de3-5efa-4e93-a2fe-0a6c8dcd6714"
        },
        {
            "timestamp_sec": 670.2152009546634,
            "timestamp_frame": 20106,
            "_unmapped_timestamp_sec": 670.23623,
            "narration_text": "#C C picks a screwdriver from the table with his left hand.",
            "annotation_uid": "ac221de3-5efa-4e93-a2fe-0a6c8dcd6714"
        },
        {
            "timestamp_sec": 675.0013609546634,
            "timestamp_frame": 20249,
            "_unmapped_timestamp_sec": 675.02239,
            "narration_text": "#C C holds the ring with his left hand.",
            "annotation_uid": "ac221de3-5efa-4e93-a2fe-0a6c8dcd6714"
        },
        {
            "timestamp_sec": 678.5966309546634,
            "timestamp_frame": 20357,
            "_unmapped_timestamp_sec": 678.61766,
            "narration_text": "#C C drops the ring and the screwdriver on the table using both hands.",
            "annotation_uid": "ac221de3-5efa-4e93-a2fe-0a6c8dcd6714"
        },
        {
            "timestamp_sec": 679.5152909546633,
            "timestamp_frame": 20385,
            "_unmapped_timestamp_sec": 679.5363199999999,
            "narration_text": "#C C removes rings from the clutch with his left hand. #unsure",
            "annotation_uid": "ac221de3-5efa-4e93-a2fe-0a6c8dcd6714"
        },
        {
            "timestamp_sec": 655.4888309546634,
            "timestamp_frame": 19664,
            "_unmapped_timestamp_sec": 655.50986,
            "narration_text": "#C C moves the screwdriver from his left hand to his right hand.",
            "annotation_uid": "ac221de3-5efa-4e93-a2fe-0a6c8dcd6714"
        },
        {
            "timestamp_sec": 655.7458909546634,
            "timestamp_frame": 19672,
            "_unmapped_timestamp_sec": 655.76692,
            "narration_text": "#C C picks the tissue from the table with his left hand.",
            "annotation_uid": "ac221de3-5efa-4e93-a2fe-0a6c8dcd6714"
        },
        {
            "timestamp_sec": 662.9169109546634,
            "timestamp_frame": 19887,
            "_unmapped_timestamp_sec": 662.93794,
            "narration_text": "#C drops the ring on the table using both hands.",
            "annotation_uid": "ac221de3-5efa-4e93-a2fe-0a6c8dcd6714"
        },
        {
            "timestamp_sec": 671.6591909546634,
            "timestamp_frame": 20149,
            "_unmapped_timestamp_sec": 671.68022,
            "narration_text": "#C C moves the screwdriver from his left hand to his right hand.",
            "annotation_uid": "ac221de3-5efa-4e93-a2fe-0a6c8dcd6714"
        },
        {
            "timestamp_sec": 672.7171109546633,
            "timestamp_frame": 20181,
            "_unmapped_timestamp_sec": 672.7381399999999,
            "narration_text": "#C C removes a ring from the clutch using the screwdriver in his right hand. #unsure",
            "annotation_uid": "ac221de3-5efa-4e93-a2fe-0a6c8dcd6714"
        },
        {
            "timestamp_sec": 681.9800809546634,
            "timestamp_frame": 20459,
            "_unmapped_timestamp_sec": 682.00111,
            "narration_text": "#C C separates the rings using his right hand. ",
            "annotation_uid": "ac221de3-5efa-4e93-a2fe-0a6c8dcd6714"
        },
        {
            "timestamp_sec": 684.8021609546635,
            "timestamp_frame": 20543,
            "_unmapped_timestamp_sec": 684.8231900000001,
            "narration_text": "#C C drops the ring on the table with his right hand.",
            "annotation_uid": "ac221de3-5efa-4e93-a2fe-0a6c8dcd6714"
        },
        {
            "timestamp_sec": 686.1648709546633,
            "timestamp_frame": 20584,
            "_unmapped_timestamp_sec": 686.1859,
            "narration_text": "#C C removes rings from the clutch with his right hand. #unsure",
            "annotation_uid": "ac221de3-5efa-4e93-a2fe-0a6c8dcd6714"
        },
        {
            "timestamp_sec": 690.5456209546634,
            "timestamp_frame": 20716,
            "_unmapped_timestamp_sec": 690.56665,
            "narration_text": "#C C moves the ring from his right hand to his left hand.",
            "annotation_uid": "ac221de3-5efa-4e93-a2fe-0a6c8dcd6714"
        },
        {
            "timestamp_sec": 691.4544209546634,
            "timestamp_frame": 20743,
            "_unmapped_timestamp_sec": 691.47545,
            "narration_text": "#C C drops the ring on the table with his right hand.",
            "annotation_uid": "ac221de3-5efa-4e93-a2fe-0a6c8dcd6714"
        },
        {
            "timestamp_sec": 692.3909109546634,
            "timestamp_frame": 20771,
            "_unmapped_timestamp_sec": 692.41194,
            "narration_text": "#C C holds the ring with both hands.",
            "annotation_uid": "ac221de3-5efa-4e93-a2fe-0a6c8dcd6714"
        },
        {
            "timestamp_sec": 692.9760809546634,
            "timestamp_frame": 20789,
            "_unmapped_timestamp_sec": 692.99711,
            "narration_text": "#C C removes a ring from the clutch with his right hand. #unsure",
            "annotation_uid": "ac221de3-5efa-4e93-a2fe-0a6c8dcd6714"
        },
        {
            "timestamp_sec": 694.9043309546634,
            "timestamp_frame": 20846,
            "_unmapped_timestamp_sec": 694.92536,
            "narration_text": "#C C drops the rings on the table with his left hand.",
            "annotation_uid": "ac221de3-5efa-4e93-a2fe-0a6c8dcd6714"
        },
        {
            "timestamp_sec": 697.1463109546634,
            "timestamp_frame": 20914,
            "_unmapped_timestamp_sec": 697.16734,
            "narration_text": "#C C holds the ring with both hands.",
            "annotation_uid": "ac221de3-5efa-4e93-a2fe-0a6c8dcd6714"
        },
        {
            "timestamp_sec": 704.3087309546634,
            "timestamp_frame": 21129,
            "_unmapped_timestamp_sec": 704.32976,
            "narration_text": "#C C unscrews the ring with his left hand. #unsure",
            "annotation_uid": "ac221de3-5efa-4e93-a2fe-0a6c8dcd6714"
        },
        {
            "timestamp_sec": 698.6886309546634,
            "timestamp_frame": 20960,
            "_unmapped_timestamp_sec": 698.70966,
            "narration_text": "#C C touches the clutch with his right hand.",
            "annotation_uid": "ac221de3-5efa-4e93-a2fe-0a6c8dcd6714"
        },
        {
            "timestamp_sec": 707.6615809546635,
            "timestamp_frame": 21229,
            "_unmapped_timestamp_sec": 707.6826100000001,
            "narration_text": "#C C screws the nut on the clutch with his right hand. #unsure",
            "annotation_uid": "ac221de3-5efa-4e93-a2fe-0a6c8dcd6714"
        },
        {
            "timestamp_sec": 707.2918609546634,
            "timestamp_frame": 21218,
            "_unmapped_timestamp_sec": 707.31289,
            "narration_text": "#C C removes a nut from the ring with his right hand. #unsure",
            "annotation_uid": "ac221de3-5efa-4e93-a2fe-0a6c8dcd6714"
        },
        {
            "timestamp_sec": 710.1184809546634,
            "timestamp_frame": 21303,
            "_unmapped_timestamp_sec": 710.13951,
            "narration_text": "#C C places the ring on the clutch with his left hand. #unsure",
            "annotation_uid": "ac221de3-5efa-4e93-a2fe-0a6c8dcd6714"
        },
        {
            "timestamp_sec": 711.1073809546634,
            "timestamp_frame": 21333,
            "_unmapped_timestamp_sec": 711.12841,
            "narration_text": "#C C screws the ring on the clutch with his left hand. #unsure",
            "annotation_uid": "ac221de3-5efa-4e93-a2fe-0a6c8dcd6714"
        },
        {
            "timestamp_sec": 717.1708909546634,
            "timestamp_frame": 21514,
            "_unmapped_timestamp_sec": 717.19192,
            "narration_text": "#C C picks the tissue from the table with his right hand.",
            "annotation_uid": "ac221de3-5efa-4e93-a2fe-0a6c8dcd6714"
        },
        {
            "timestamp_sec": 717.7292209546634,
            "timestamp_frame": 21531,
            "_unmapped_timestamp_sec": 717.75025,
            "narration_text": "#C C cleans both hands on the tissue.",
            "annotation_uid": "ac221de3-5efa-4e93-a2fe-0a6c8dcd6714"
        },
        {
            "timestamp_sec": 719.9640309546634,
            "timestamp_frame": 21598,
            "_unmapped_timestamp_sec": 719.98506,
            "narration_text": "#C C picks a gear wheel from a tool container. #unsure",
            "annotation_uid": "ac221de3-5efa-4e93-a2fe-0a6c8dcd6714"
        },
        {
            "timestamp_sec": 725.2540609546634,
            "timestamp_frame": 21757,
            "_unmapped_timestamp_sec": 725.27509,
            "narration_text": "#C C cleans both hands on the tissue.",
            "annotation_uid": "ac221de3-5efa-4e93-a2fe-0a6c8dcd6714"
        },
        {
            "timestamp_sec": 728.3916909546634,
            "timestamp_frame": 21851,
            "_unmapped_timestamp_sec": 728.41272,
            "narration_text": "#C C raises his right hand.",
            "annotation_uid": "ac221de3-5efa-4e93-a2fe-0a6c8dcd6714"
        },
        {
            "timestamp_sec": 600.7740409546634,
            "timestamp_frame": 18023,
            "_unmapped_timestamp_sec": 600.79507,
            "narration_text": "#C C hits #unsure",
            "annotation_uid": "fe4cb02f-ae31-41b6-9171-f3a74935b76c"
        },
        {
            "timestamp_sec": 603.5243209546634,
            "timestamp_frame": 18105,
            "_unmapped_timestamp_sec": 603.54535,
            "narration_text": "#C C touches #unsure",
            "annotation_uid": "fe4cb02f-ae31-41b6-9171-f3a74935b76c"
        },
        {
            "timestamp_sec": 608.0428109546634,
            "timestamp_frame": 18241,
            "_unmapped_timestamp_sec": 608.06384,
            "narration_text": "#C C puts the hammer on the table",
            "annotation_uid": "fe4cb02f-ae31-41b6-9171-f3a74935b76c"
        },
        {
            "timestamp_sec": 610.3135209546634,
            "timestamp_frame": 18309,
            "_unmapped_timestamp_sec": 610.33455,
            "narration_text": "#C C adjusts #unsure",
            "annotation_uid": "fe4cb02f-ae31-41b6-9171-f3a74935b76c"
        },
        {
            "timestamp_sec": 613.0817609546634,
            "timestamp_frame": 18392,
            "_unmapped_timestamp_sec": 613.10279,
            "narration_text": "#C C holds #unsure with the left hand",
            "annotation_uid": "fe4cb02f-ae31-41b6-9171-f3a74935b76c"
        },
        {
            "timestamp_sec": 614.6627909546634,
            "timestamp_frame": 18439,
            "_unmapped_timestamp_sec": 614.68382,
            "narration_text": "#C C wipes hand",
            "annotation_uid": "fe4cb02f-ae31-41b6-9171-f3a74935b76c"
        },
        {
            "timestamp_sec": 615.9708209546634,
            "timestamp_frame": 18478,
            "_unmapped_timestamp_sec": 615.99185,
            "narration_text": "#C C holds #unsure with the left hand",
            "annotation_uid": "fe4cb02f-ae31-41b6-9171-f3a74935b76c"
        },
        {
            "timestamp_sec": 618.0877709546634,
            "timestamp_frame": 18542,
            "_unmapped_timestamp_sec": 618.1088,
            "narration_text": "#C C picks #unsure",
            "annotation_uid": "fe4cb02f-ae31-41b6-9171-f3a74935b76c"
        },
        {
            "timestamp_sec": 619.6637109546634,
            "timestamp_frame": 18589,
            "_unmapped_timestamp_sec": 619.68474,
            "narration_text": "#C C looks at #unsure",
            "annotation_uid": "fe4cb02f-ae31-41b6-9171-f3a74935b76c"
        },
        {
            "timestamp_sec": 624.5119409546634,
            "timestamp_frame": 18735,
            "_unmapped_timestamp_sec": 624.53297,
            "narration_text": "#C C moves the hammer",
            "annotation_uid": "fe4cb02f-ae31-41b6-9171-f3a74935b76c"
        },
        {
            "timestamp_sec": 626.4587809546634,
            "timestamp_frame": 18793,
            "_unmapped_timestamp_sec": 626.47981,
            "narration_text": "#C C stretches' hand on the display",
            "annotation_uid": "fe4cb02f-ae31-41b6-9171-f3a74935b76c"
        },
        {
            "timestamp_sec": 628.1258409546634,
            "timestamp_frame": 18843,
            "_unmapped_timestamp_sec": 628.14687,
            "narration_text": "#C C picks a bolt",
            "annotation_uid": "fe4cb02f-ae31-41b6-9171-f3a74935b76c"
        },
        {
            "timestamp_sec": 629.0648609546635,
            "timestamp_frame": 18871,
            "_unmapped_timestamp_sec": 629.0858900000001,
            "narration_text": "#C C adjusts the bolt",
            "annotation_uid": "fe4cb02f-ae31-41b6-9171-f3a74935b76c"
        },
        {
            "timestamp_sec": 630.4683909546634,
            "timestamp_frame": 18913,
            "_unmapped_timestamp_sec": 630.48942,
            "narration_text": "#C C puts the bolt in the clutch plate disc",
            "annotation_uid": "fe4cb02f-ae31-41b6-9171-f3a74935b76c"
        },
        {
            "timestamp_sec": 631.9603709546634,
            "timestamp_frame": 18958,
            "_unmapped_timestamp_sec": 631.9814,
            "narration_text": "#C C picks a clutch plate",
            "annotation_uid": "fe4cb02f-ae31-41b6-9171-f3a74935b76c"
        },
        {
            "timestamp_sec": 633.7473409546634,
            "timestamp_frame": 19012,
            "_unmapped_timestamp_sec": 633.76837,
            "narration_text": "#C C fits the bolt in the clutch plate disc",
            "annotation_uid": "fe4cb02f-ae31-41b6-9171-f3a74935b76c"
        },
        {
            "timestamp_sec": 634.5618709546634,
            "timestamp_frame": 19036,
            "_unmapped_timestamp_sec": 634.5829,
            "narration_text": "#C C drops the rag on the table",
            "annotation_uid": "fe4cb02f-ae31-41b6-9171-f3a74935b76c"
        },
        {
            "timestamp_sec": 636.0046309546634,
            "timestamp_frame": 19080,
            "_unmapped_timestamp_sec": 636.02566,
            "narration_text": "#C C tightens the bolt on the  clutch plate disc",
            "annotation_uid": "fe4cb02f-ae31-41b6-9171-f3a74935b76c"
        },
        {
            "timestamp_sec": 640.0513109546633,
            "timestamp_frame": 19201,
            "_unmapped_timestamp_sec": 640.0723399999999,
            "narration_text": "#C C picks a spanner from the display",
            "annotation_uid": "fe4cb02f-ae31-41b6-9171-f3a74935b76c"
        },
        {
            "timestamp_sec": 641.6157809546634,
            "timestamp_frame": 19248,
            "_unmapped_timestamp_sec": 641.63681,
            "narration_text": "#C C tightens the bolt",
            "annotation_uid": "fe4cb02f-ae31-41b6-9171-f3a74935b76c"
        },
        {
            "timestamp_sec": 644.7700109546633,
            "timestamp_frame": 19342,
            "_unmapped_timestamp_sec": 644.79104,
            "narration_text": "#C C drops the spanner",
            "annotation_uid": "fe4cb02f-ae31-41b6-9171-f3a74935b76c"
        },
        {
            "timestamp_sec": 645.9133609546634,
            "timestamp_frame": 19377,
            "_unmapped_timestamp_sec": 645.93439,
            "narration_text": "#C C moves the cable",
            "annotation_uid": "fe4cb02f-ae31-41b6-9171-f3a74935b76c"
        },
        {
            "timestamp_sec": 647.4017309546634,
            "timestamp_frame": 19421,
            "_unmapped_timestamp_sec": 647.42276,
            "narration_text": "#C C touches #unsure",
            "annotation_uid": "fe4cb02f-ae31-41b6-9171-f3a74935b76c"
        },
        {
            "timestamp_sec": 648.6675709546633,
            "timestamp_frame": 19459,
            "_unmapped_timestamp_sec": 648.6886,
            "narration_text": "#C C puts the clutch plate cover on #unsure",
            "annotation_uid": "fe4cb02f-ae31-41b6-9171-f3a74935b76c"
        },
        {
            "timestamp_sec": 650.2660509546635,
            "timestamp_frame": 19507,
            "_unmapped_timestamp_sec": 650.2870800000001,
            "narration_text": "#C C tightens the clutch plate cover",
            "annotation_uid": "fe4cb02f-ae31-41b6-9171-f3a74935b76c"
        },
        {
            "timestamp_sec": 652.7141409546634,
            "timestamp_frame": 19581,
            "_unmapped_timestamp_sec": 652.73517,
            "narration_text": "#C C flips fingers",
            "annotation_uid": "fe4cb02f-ae31-41b6-9171-f3a74935b76c"
        },
        {
            "timestamp_sec": 655.0418409546634,
            "timestamp_frame": 19651,
            "_unmapped_timestamp_sec": 655.06287,
            "narration_text": "#C C picks a screw driver driver",
            "annotation_uid": "fe4cb02f-ae31-41b6-9171-f3a74935b76c"
        },
        {
            "timestamp_sec": 656.6845909546633,
            "timestamp_frame": 19700,
            "_unmapped_timestamp_sec": 656.70562,
            "narration_text": "#C C wipes the screw driver",
            "annotation_uid": "fe4cb02f-ae31-41b6-9171-f3a74935b76c"
        },
        {
            "timestamp_sec": 660.9955209546634,
            "timestamp_frame": 19829,
            "_unmapped_timestamp_sec": 661.01655,
            "narration_text": "#C C unscrews the car ring",
            "annotation_uid": "fe4cb02f-ae31-41b6-9171-f3a74935b76c"
        },
        {
            "timestamp_sec": 662.2533509546633,
            "timestamp_frame": 19867,
            "_unmapped_timestamp_sec": 662.27438,
            "narration_text": "#C C removes the car ring",
            "annotation_uid": "fe4cb02f-ae31-41b6-9171-f3a74935b76c"
        },
        {
            "timestamp_sec": 663.2439509546634,
            "timestamp_frame": 19897,
            "_unmapped_timestamp_sec": 663.26498,
            "narration_text": "#C C puts the car ring on the table",
            "annotation_uid": "fe4cb02f-ae31-41b6-9171-f3a74935b76c"
        },
        {
            "timestamp_sec": 665.6304209546634,
            "timestamp_frame": 19968,
            "_unmapped_timestamp_sec": 665.65145,
            "narration_text": "#C C pulls the clutch plate disc",
            "annotation_uid": "fe4cb02f-ae31-41b6-9171-f3a74935b76c"
        },
        {
            "timestamp_sec": 668.0420109546634,
            "timestamp_frame": 20041,
            "_unmapped_timestamp_sec": 668.06304,
            "narration_text": "#C C flips fingers",
            "annotation_uid": "fe4cb02f-ae31-41b6-9171-f3a74935b76c"
        },
        {
            "timestamp_sec": 670.2549909546634,
            "timestamp_frame": 20107,
            "_unmapped_timestamp_sec": 670.27602,
            "narration_text": "#C C holds a screw driver",
            "annotation_uid": "fe4cb02f-ae31-41b6-9171-f3a74935b76c"
        },
        {
            "timestamp_sec": 671.9668309546634,
            "timestamp_frame": 20158,
            "_unmapped_timestamp_sec": 671.98786,
            "narration_text": "#C C picks a screw driver",
            "annotation_uid": "fe4cb02f-ae31-41b6-9171-f3a74935b76c"
        },
        {
            "timestamp_sec": 673.9341909546634,
            "timestamp_frame": 20217,
            "_unmapped_timestamp_sec": 673.95522,
            "narration_text": "#C C adjusts the clutch plate disc",
            "annotation_uid": "fe4cb02f-ae31-41b6-9171-f3a74935b76c"
        },
        {
            "timestamp_sec": 676.8117209546634,
            "timestamp_frame": 20304,
            "_unmapped_timestamp_sec": 676.83275,
            "narration_text": "#C C removes #unsure from the clutch plate disc",
            "annotation_uid": "fe4cb02f-ae31-41b6-9171-f3a74935b76c"
        },
        {
            "timestamp_sec": 678.5213409546634,
            "timestamp_frame": 20355,
            "_unmapped_timestamp_sec": 678.54237,
            "narration_text": "#C C puts #unsure and the screw driver on the table",
            "annotation_uid": "fe4cb02f-ae31-41b6-9171-f3a74935b76c"
        },
        {
            "timestamp_sec": 680.8416109546635,
            "timestamp_frame": 20425,
            "_unmapped_timestamp_sec": 680.86264,
            "narration_text": "#C C removes #unsure from the clutch plate disc",
            "annotation_uid": "fe4cb02f-ae31-41b6-9171-f3a74935b76c"
        },
        {
            "timestamp_sec": 683.1755309546634,
            "timestamp_frame": 20495,
            "_unmapped_timestamp_sec": 683.19656,
            "narration_text": "#C C opens #unsure",
            "annotation_uid": "fe4cb02f-ae31-41b6-9171-f3a74935b76c"
        },
        {
            "timestamp_sec": 685.0879809546634,
            "timestamp_frame": 20552,
            "_unmapped_timestamp_sec": 685.10901,
            "narration_text": "#C C puts #unsure on the table",
            "annotation_uid": "fe4cb02f-ae31-41b6-9171-f3a74935b76c"
        },
        {
            "timestamp_sec": 688.6701009546633,
            "timestamp_frame": 20659,
            "_unmapped_timestamp_sec": 688.6911299999999,
            "narration_text": "#C C removes #unsure from the clutch plate disc",
            "annotation_uid": "fe4cb02f-ae31-41b6-9171-f3a74935b76c"
        },
        {
            "timestamp_sec": 691.0304609546635,
            "timestamp_frame": 20730,
            "_unmapped_timestamp_sec": 691.0514900000001,
            "narration_text": "#C C puts #unsure together",
            "annotation_uid": "fe4cb02f-ae31-41b6-9171-f3a74935b76c"
        },
        {
            "timestamp_sec": 691.7064009546634,
            "timestamp_frame": 20751,
            "_unmapped_timestamp_sec": 691.72743,
            "narration_text": "#C C puts #umsure on the table",
            "annotation_uid": "fe4cb02f-ae31-41b6-9171-f3a74935b76c"
        },
        {
            "timestamp_sec": 694.4541009546634,
            "timestamp_frame": 20833,
            "_unmapped_timestamp_sec": 694.47513,
            "narration_text": "#C C removes #unsure from the clutch plate disc",
            "annotation_uid": "fe4cb02f-ae31-41b6-9171-f3a74935b76c"
        },
        {
            "timestamp_sec": 695.5245809546634,
            "timestamp_frame": 20865,
            "_unmapped_timestamp_sec": 695.54561,
            "narration_text": "#C C puts #unsure on the table",
            "annotation_uid": "fe4cb02f-ae31-41b6-9171-f3a74935b76c"
        },
        {
            "timestamp_sec": 697.1973809546633,
            "timestamp_frame": 20915,
            "_unmapped_timestamp_sec": 697.21841,
            "narration_text": "#C C picks #unsure from the right hand",
            "annotation_uid": "fe4cb02f-ae31-41b6-9171-f3a74935b76c"
        },
        {
            "timestamp_sec": 698.5218909546634,
            "timestamp_frame": 20955,
            "_unmapped_timestamp_sec": 698.54292,
            "narration_text": "#C C touches the clutch disc plate",
            "annotation_uid": "fe4cb02f-ae31-41b6-9171-f3a74935b76c"
        },
        {
            "timestamp_sec": 705.9476609546634,
            "timestamp_frame": 21178,
            "_unmapped_timestamp_sec": 705.96869,
            "narration_text": "#C C adjusts the clutch disc plate",
            "annotation_uid": "fe4cb02f-ae31-41b6-9171-f3a74935b76c"
        },
        {
            "timestamp_sec": 707.3350409546634,
            "timestamp_frame": 21219,
            "_unmapped_timestamp_sec": 707.35607,
            "narration_text": "#C C removes a bolt from the clutch disc plate",
            "annotation_uid": "fe4cb02f-ae31-41b6-9171-f3a74935b76c"
        },
        {
            "timestamp_sec": 708.0526609546633,
            "timestamp_frame": 21241,
            "_unmapped_timestamp_sec": 708.0736899999999,
            "narration_text": "#C C puts the bolt in the clutch disc plate",
            "annotation_uid": "fe4cb02f-ae31-41b6-9171-f3a74935b76c"
        },
        {
            "timestamp_sec": 710.5641109546634,
            "timestamp_frame": 21316,
            "_unmapped_timestamp_sec": 710.58514,
            "narration_text": "#C puts #unsure on the clutch disc plate",
            "annotation_uid": "fe4cb02f-ae31-41b6-9171-f3a74935b76c"
        },
        {
            "timestamp_sec": 717.6715709546634,
            "timestamp_frame": 21530,
            "_unmapped_timestamp_sec": 717.6926,
            "narration_text": "#C C picks a rag",
            "annotation_uid": "fe4cb02f-ae31-41b6-9171-f3a74935b76c"
        },
        {
            "timestamp_sec": 718.3010709546634,
            "timestamp_frame": 21548,
            "_unmapped_timestamp_sec": 718.3221,
            "narration_text": "#C C wipes hands",
            "annotation_uid": "fe4cb02f-ae31-41b6-9171-f3a74935b76c"
        },
        {
            "timestamp_sec": 721.0603409546634,
            "timestamp_frame": 21631,
            "_unmapped_timestamp_sec": 721.08137,
            "narration_text": "#C C picks an engine from the tool box",
            "annotation_uid": "fe4cb02f-ae31-41b6-9171-f3a74935b76c"
        },
        {
            "timestamp_sec": 724.3927309546634,
            "timestamp_frame": 21731,
            "_unmapped_timestamp_sec": 724.41376,
            "narration_text": "#C C puts the engine drive in the tool box",
            "annotation_uid": "fe4cb02f-ae31-41b6-9171-f3a74935b76c"
        },
        {
            "timestamp_sec": 725.5725109546634,
            "timestamp_frame": 21767,
            "_unmapped_timestamp_sec": 725.59354,
            "narration_text": "#C C wipes fingers",
            "annotation_uid": "fe4cb02f-ae31-41b6-9171-f3a74935b76c"
        }
    ]
}